hitoshura25_pypi_workflow_generator/README.md
hitoshura25_pypi_workflow_generator/__init__.py
hitoshura25_pypi_workflow_generator/_reusable_test_build.yml.j2
hitoshura25_pypi_workflow_generator/create_release.py
hitoshura25_pypi_workflow_generator/create_release.yml.j2
hitoshura25_pypi_workflow_generator/generator.py
hitoshura25_pypi_workflow_generator/git_utils.py
hitoshura25_pypi_workflow_generator/init.py
hitoshura25_pypi_workflow_generator/main.py
hitoshura25_pypi_workflow_generator/pypi_publish.yml.j2
hitoshura25_pypi_workflow_generator/pyproject.toml.j2
hitoshura25_pypi_workflow_generator/release.yml.j2
hitoshura25_pypi_workflow_generator/release_workflow.py
hitoshura25_pypi_workflow_generator/server.py
hitoshura25_pypi_workflow_generator/setup.py.j2
hitoshura25_pypi_workflow_generator/test_pr.yml.j2
hitoshura25_pypi_workflow_generator/scripts/calculate_version.sh.j2
hitoshura25_pypi_workflow_generator/tests/__init__.py
hitoshura25_pypi_workflow_generator/tests/test_calculate_version.py
hitoshura25_pypi_workflow_generator/tests/test_generator.py
hitoshura25_pypi_workflow_generator/tests/test_git_utils.py
hitoshura25_pypi_workflow_generator/tests/test_init.py
hitoshura25_pypi_workflow_generator/tests/test_release_workflow.py
hitoshura25_pypi_workflow_generator/tests/test_server.py
hitoshura25_pypi_workflow_generator-0.6.0.dist-info/licenses/LICENSE
hitoshura25_pypi_workflow_generator-0.6.0.dist-info/METADATA
hitoshura25_pypi_workflow_generator-0.6.0.dist-info/WHEEL
hitoshura25_pypi_workflow_generator-0.6.0.dist-info/entry_points.txt
hitoshura25_pypi_workflow_generator-0.6.0.dist-info/top_level.txt
hitoshura25_pypi_workflow_generator-0.6.0.dist-info/RECORD
