Metadata-Version: 2.4
Name: hitoshura25-pypi-workflow-generator
Version: 0.6.0
Summary: Dual-mode tool (MCP server + CLI) for generating GitHub Actions workflows
Home-page: https://github.com/hitoshura25/pypi-workflow-generator
Author: Vinayak Menon
Author-email: Vinayak Menon <vinayakmenon+pypi@users.noreply.github.com>
License: Apache-2.0
Project-URL: Homepage, https://github.com/hitoshura25/pypi-workflow-generator
Project-URL: Repository, https://github.com/hitoshura25/pypi-workflow-generator
Project-URL: Issues, https://github.com/hitoshura25/pypi-workflow-generator/issues
Project-URL: Documentation, https://github.com/hitoshura25/pypi-workflow-generator/blob/main/README.md
Keywords: mcp,github-actions,pypi,workflow,ci-cd,code-generator
Classifier: Programming Language :: Python :: 3
Classifier: Programming Language :: Python :: 3.8
Classifier: Programming Language :: Python :: 3.9
Classifier: Programming Language :: Python :: 3.10
Classifier: Programming Language :: Python :: 3.11
Classifier: Programming Language :: Python :: 3.12
Classifier: License :: OSI Approved :: Apache Software License
Classifier: Operating System :: OS Independent
Classifier: Development Status :: 3 - Alpha
Classifier: Intended Audience :: Developers
Classifier: Topic :: Software Development :: Code Generators
Classifier: Topic :: Software Development :: Build Tools
Requires-Python: >=3.8
License-File: LICENSE
Requires-Dist: Jinja2>=3.0
Requires-Dist: pyyaml
Provides-Extra: test
Requires-Dist: pytest; extra == "test"
Requires-Dist: pytest-asyncio; extra == "test"
Provides-Extra: dev
Requires-Dist: twine; extra == "dev"
Requires-Dist: wheel; extra == "dev"
Requires-Dist: setuptools_scm; extra == "dev"
Requires-Dist: build; extra == "dev"
Requires-Dist: ruff; extra == "dev"
Dynamic: author
Dynamic: home-page
Dynamic: license-file
Dynamic: requires-python
